thmap/__init__.py
thmap/classify.py
thmap/io.py
thmap-0.0.2.dist-info/METADATA
thmap-0.0.2.dist-info/WHEEL
thmap-0.0.2.dist-info/top_level.txt
thmap-0.0.2.dist-info/RECORD
